README.md
setup.cfg
setup.py
limestone/__init__.py
limestone/api_client.py
limestone/configuration.py
limestone/exceptions.py
limestone/rest.py
limestone.egg-info/PKG-INFO
limestone.egg-info/SOURCES.txt
limestone.egg-info/dependency_links.txt
limestone.egg-info/requires.txt
limestone.egg-info/top_level.txt
limestone/api/__init__.py
limestone/api/core_api.py
limestone/api/facility_api.py
limestone/api/image_api.py
limestone/api/job_api.py
limestone/api/project_api.py
limestone/api/ssh_key_api.py
limestone/models/__init__.py
limestone/models/core.py
limestone/models/disk.py
limestone/models/facility.py
limestone/models/facility_stock.py
limestone/models/image.py
limestone/models/inline_object.py
limestone/models/inline_object1.py
limestone/models/inline_object2.py
limestone/models/inline_response200.py
limestone/models/instance.py
limestone/models/job_status.py
limestone/models/metadata.py
limestone/models/partition_disk.py
limestone/models/partition_disk_all_of.py
limestone/models/project.py
limestone/models/project_quotas.py
limestone/models/raid_disk.py
limestone/models/raid_disk_all_of.py
limestone/models/raid_disk_all_of_raid.py
limestone/models/result.py
limestone/models/server.py
limestone/models/server_create.py
limestone/models/server_create_parameters.py
limestone/models/server_create_parameters_with_os_disk.py
limestone/models/server_create_parameters_with_os_disk_all_of.py
limestone/models/server_create_parameters_with_partitions.py
limestone/models/server_create_parameters_with_partitions_all_of.py
limestone/models/server_create_validation_error.py
limestone/models/server_create_validation_error_response.py
limestone/models/ssh_key.py
test/test_core.py
test/test_core_api.py
test/test_disk.py
test/test_facility.py
test/test_facility_api.py
test/test_facility_stock.py
test/test_image.py
test/test_image_api.py
test/test_inline_object.py
test/test_inline_object1.py
test/test_inline_object2.py
test/test_inline_response200.py
test/test_instance.py
test/test_job_api.py
test/test_job_status.py
test/test_metadata.py
test/test_partition_disk.py
test/test_partition_disk_all_of.py
test/test_project.py
test/test_project_api.py
