Metadata-Version: 1.0
Name: limestone
Version: 1.0.0
Summary: Limestone Networks API
Home-page: UNKNOWN
Author: UNKNOWN
Author-email: support@limestonenetworks.com
License: UNKNOWN
Keywords: OpenAPI,OpenAPI-Generator,Limestone Networks API
Platform: UNKNOWN
